setup.py
django_kicker.egg-info/PKG-INFO
django_kicker.egg-info/SOURCES.txt
django_kicker.egg-info/dependency_links.txt
django_kicker.egg-info/top_level.txt
kicker/__init__.py
kicker/broker.py
kicker/models.py
kicker/urls.py
kicker/views.py